{
    "@context": "http://www.shared-canvas.org/ns/context.json",
    "@id": "https://raw.githubusercontent.com/nakamura196/omekac_utda/master/docs/oa/items/4403/annolist.json",
    "@type": "sc:AnnotationList",
    "resources": [
        {
            "@context": "http://iiif.io/api/presentation/2/context.json",
            "@id": "https://iiif.dl.itc.u-tokyo.ac.jp/omekac/oa/items/4548/anno.json",
            "@type": "oa:Annotation",
            "motivation": "oa:commenting",
            "on": [
                {
                    "@type": "oa:SpecificResource",
                    "full": "https://iiif.dl.itc.u-tokyo.ac.jp/repo/iiif/bbe39586-8623-447b-8814-0e19c3986d05/canvas/p5",
                    "selector": {
                        "@type": "oa:Choice",
                        "default": {
                            "@type": "oa:FragmentSelector",
                            "value": "xywh=4959,0,218,5035"
                        },
                        "item": {
                            "@type": "oa:SvgSelector",
                            "value": "<svg xmlns=\"http://www.w3.org/2000/svg\"><path xmlns=\"http://www.w3.org/2000/svg\" d=\"M5177,5035h-218v-5035h218v2517.5z\" data-paper-data=\"{&quot;strokeWidth&quot;:1,&quot;rotation&quot;:0,&quot;deleteIcon&quot;:null,&quot;rotationIcon&quot;:null,&quot;group&quot;:null,&quot;editable&quot;:true,&quot;annotation&quot;:null}\" id=\"rectangle_1d3ebadc-1bcd-4e07-8cc2-c95d2f1865b7\" fill-opacity=\"0\" fill=\"#00bfff\" fill-rule=\"nonzero\" stroke=\"#00bfff\" stroke-width=\"1\" stroke-linecap=\"butt\" stroke-linejoin=\"miter\" stroke-miterlimit=\"10\" stroke-dasharray=\"\" stroke-dashoffset=\"0\" font-family=\"none\" font-weight=\"none\" font-size=\"none\" text-anchor=\"none\" style=\"mix-blend-mode: normal\"/></svg>"
                        }
                    },
                    "within": {
                        "@id": "https://raw.githubusercontent.com/nakamura196/omekac_utda/master/docs/oa/items/4403/manifest.json",
                        "@type": "sc:Manifest"
                    }
                }
            ],
            "resource": [
                {
                    "@type": "dctypes:Text",
                    "chars": "<p>A006267-01-0005.jpg_1</p>",
                    "format": "text/html"
                }
            ]
        },
        {
            "@context": "http://iiif.io/api/presentation/2/context.json",
            "@id": "https://iiif.dl.itc.u-tokyo.ac.jp/omekac/oa/items/4549/anno.json",
            "@type": "oa:Annotation",
            "motivation": "oa:commenting",
            "on": [
                {
                    "@type": "oa:SpecificResource",
                    "full": "https://iiif.dl.itc.u-tokyo.ac.jp/repo/iiif/bbe39586-8623-447b-8814-0e19c3986d05/canvas/p5",
                    "selector": {
                        "@type": "oa:Choice",
                        "default": {
                            "@type": "oa:FragmentSelector",
                            "value": "xywh=4539,0,234,5035"
                        },
                        "item": {
                            "@type": "oa:SvgSelector",
                            "value": "<svg xmlns=\"http://www.w3.org/2000/svg\"><path xmlns=\"http://www.w3.org/2000/svg\" d=\"M4773,5035h-234v-5035h234v2517.5z\" data-paper-data=\"{&quot;strokeWidth&quot;:1,&quot;rotation&quot;:0,&quot;deleteIcon&quot;:null,&quot;rotationIcon&quot;:null,&quot;group&quot;:null,&quot;editable&quot;:true,&quot;annotation&quot;:null}\" id=\"rectangle_1d3ebadc-1bcd-4e07-8cc2-c95d2f1865b7\" fill-opacity=\"0\" fill=\"#00bfff\" fill-rule=\"nonzero\" stroke=\"#00bfff\" stroke-width=\"1\" stroke-linecap=\"butt\" stroke-linejoin=\"miter\" stroke-miterlimit=\"10\" stroke-dasharray=\"\" stroke-dashoffset=\"0\" font-family=\"none\" font-weight=\"none\" font-size=\"none\" text-anchor=\"none\" style=\"mix-blend-mode: normal\"/></svg>"
                        }
                    },
                    "within": {
                        "@id": "https://iiif.dl.itc.u-tokyo.ac.jp/omekac/oa/items/4403/manifest.json",
                        "@type": "sc:Manifest"
                    }
                }
            ],
            "resource": [
                {
                    "@type": "dctypes:Text",
                    "chars": "<p>A006267-01-0005.jpg_2</p>",
                    "format": "text/html"
                }
            ]
        },
        {
            "@context": "http://iiif.io/api/presentation/2/context.json",
            "@id": "https://iiif.dl.itc.u-tokyo.ac.jp/omekac/oa/items/4550/anno.json",
            "@type": "oa:Annotation",
            "motivation": "oa:commenting",
            "on": [
                {
                    "@type": "oa:SpecificResource",
                    "full": "https://iiif.dl.itc.u-tokyo.ac.jp/repo/iiif/bbe39586-8623-447b-8814-0e19c3986d05/canvas/p5",
                    "selector": {
                        "@type": "oa:Choice",
                        "default": {
                            "@type": "oa:FragmentSelector",
                            "value": "xywh=4120,0,184,5035"
                        },
                        "item": {
                            "@type": "oa:SvgSelector",
                            "value": "<svg xmlns=\"http://www.w3.org/2000/svg\"><path xmlns=\"http://www.w3.org/2000/svg\" d=\"M4304,5035h-184v-5035h184v2517.5z\" data-paper-data=\"{&quot;strokeWidth&quot;:1,&quot;rotation&quot;:0,&quot;deleteIcon&quot;:null,&quot;rotationIcon&quot;:null,&quot;group&quot;:null,&quot;editable&quot;:true,&quot;annotation&quot;:null}\" id=\"rectangle_1d3ebadc-1bcd-4e07-8cc2-c95d2f1865b7\" fill-opacity=\"0\" fill=\"#00bfff\" fill-rule=\"nonzero\" stroke=\"#00bfff\" stroke-width=\"1\" stroke-linecap=\"butt\" stroke-linejoin=\"miter\" stroke-miterlimit=\"10\" stroke-dasharray=\"\" stroke-dashoffset=\"0\" font-family=\"none\" font-weight=\"none\" font-size=\"none\" text-anchor=\"none\" style=\"mix-blend-mode: normal\"/></svg>"
                        }
                    },
                    "within": {
                        "@id": "https://iiif.dl.itc.u-tokyo.ac.jp/omekac/oa/items/4403/manifest.json",
                        "@type": "sc:Manifest"
                    }
                }
            ],
            "resource": [
                {
                    "@type": "dctypes:Text",
                    "chars": "<p>A006267-01-0005.jpg_3</p>",
                    "format": "text/html"
                }
            ]
        },
        {
            "@context": "http://iiif.io/api/presentation/2/context.json",
            "@id": "https://iiif.dl.itc.u-tokyo.ac.jp/omekac/oa/items/4551/anno.json",
            "@type": "oa:Annotation",
            "motivation": "oa:commenting",
            "on": [
                {
                    "@type": "oa:SpecificResource",
                    "full": "https://iiif.dl.itc.u-tokyo.ac.jp/repo/iiif/bbe39586-8623-447b-8814-0e19c3986d05/canvas/p5",
                    "selector": {
                        "@type": "oa:Choice",
                        "default": {
                            "@type": "oa:FragmentSelector",
                            "value": "xywh=3709,0,193,5035"
                        },
                        "item": {
                            "@type": "oa:SvgSelector",
                            "value": "<svg xmlns=\"http://www.w3.org/2000/svg\"><path xmlns=\"http://www.w3.org/2000/svg\" d=\"M3902,5035h-193v-5035h193v2517.5z\" data-paper-data=\"{&quot;strokeWidth&quot;:1,&quot;rotation&quot;:0,&quot;deleteIcon&quot;:null,&quot;rotationIcon&quot;:null,&quot;group&quot;:null,&quot;editable&quot;:true,&quot;annotation&quot;:null}\" id=\"rectangle_1d3ebadc-1bcd-4e07-8cc2-c95d2f1865b7\" fill-opacity=\"0\" fill=\"#00bfff\" fill-rule=\"nonzero\" stroke=\"#00bfff\" stroke-width=\"1\" stroke-linecap=\"butt\" stroke-linejoin=\"miter\" stroke-miterlimit=\"10\" stroke-dasharray=\"\" stroke-dashoffset=\"0\" font-family=\"none\" font-weight=\"none\" font-size=\"none\" text-anchor=\"none\" style=\"mix-blend-mode: normal\"/></svg>"
                        }
                    },
                    "within": {
                        "@id": "https://iiif.dl.itc.u-tokyo.ac.jp/omekac/oa/items/4403/manifest.json",
                        "@type": "sc:Manifest"
                    }
                }
            ],
            "resource": [
                {
                    "@type": "dctypes:Text",
                    "chars": "<p>A006267-01-0005.jpg_4</p>",
                    "format": "text/html"
                }
            ]
        },
        {
            "@context": "http://iiif.io/api/presentation/2/context.json",
            "@id": "https://iiif.dl.itc.u-tokyo.ac.jp/omekac/oa/items/4552/anno.json",
            "@type": "oa:Annotation",
            "motivation": "oa:commenting",
            "on": [
                {
                    "@type": "oa:SpecificResource",
                    "full": "https://iiif.dl.itc.u-tokyo.ac.jp/repo/iiif/bbe39586-8623-447b-8814-0e19c3986d05/canvas/p5",
                    "selector": {
                        "@type": "oa:Choice",
                        "default": {
                            "@type": "oa:FragmentSelector",
                            "value": "xywh=3272,0,184,5035"
                        },
                        "item": {
                            "@type": "oa:SvgSelector",
                            "value": "<svg xmlns=\"http://www.w3.org/2000/svg\"><path xmlns=\"http://www.w3.org/2000/svg\" d=\"M3456,5035h-184v-5035h184v2517.5z\" data-paper-data=\"{&quot;strokeWidth&quot;:1,&quot;rotation&quot;:0,&quot;deleteIcon&quot;:null,&quot;rotationIcon&quot;:null,&quot;group&quot;:null,&quot;editable&quot;:true,&quot;annotation&quot;:null}\" id=\"rectangle_1d3ebadc-1bcd-4e07-8cc2-c95d2f1865b7\" fill-opacity=\"0\" fill=\"#00bfff\" fill-rule=\"nonzero\" stroke=\"#00bfff\" stroke-width=\"1\" stroke-linecap=\"butt\" stroke-linejoin=\"miter\" stroke-miterlimit=\"10\" stroke-dasharray=\"\" stroke-dashoffset=\"0\" font-family=\"none\" font-weight=\"none\" font-size=\"none\" text-anchor=\"none\" style=\"mix-blend-mode: normal\"/></svg>"
                        }
                    },
                    "within": {
                        "@id": "https://iiif.dl.itc.u-tokyo.ac.jp/omekac/oa/items/4403/manifest.json",
                        "@type": "sc:Manifest"
                    }
                }
            ],
            "resource": [
                {
                    "@type": "dctypes:Text",
                    "chars": "<p>A006267-01-0005.jpg_5</p>",
                    "format": "text/html"
                }
            ]
        },
        {
            "@context": "http://iiif.io/api/presentation/2/context.json",
            "@id": "https://iiif.dl.itc.u-tokyo.ac.jp/omekac/oa/items/4553/anno.json",
            "@type": "oa:Annotation",
            "motivation": "oa:commenting",
            "on": [
                {
                    "@type": "oa:SpecificResource",
                    "full": "https://iiif.dl.itc.u-tokyo.ac.jp/repo/iiif/bbe39586-8623-447b-8814-0e19c3986d05/canvas/p5",
                    "selector": {
                        "@type": "oa:Choice",
                        "default": {
                            "@type": "oa:FragmentSelector",
                            "value": "xywh=2987,0,159,5035"
                        },
                        "item": {
                            "@type": "oa:SvgSelector",
                            "value": "<svg xmlns=\"http://www.w3.org/2000/svg\"><path xmlns=\"http://www.w3.org/2000/svg\" d=\"M3146,5035h-159v-5035h159v2517.5z\" data-paper-data=\"{&quot;strokeWidth&quot;:1,&quot;rotation&quot;:0,&quot;deleteIcon&quot;:null,&quot;rotationIcon&quot;:null,&quot;group&quot;:null,&quot;editable&quot;:true,&quot;annotation&quot;:null}\" id=\"rectangle_1d3ebadc-1bcd-4e07-8cc2-c95d2f1865b7\" fill-opacity=\"0\" fill=\"#00bfff\" fill-rule=\"nonzero\" stroke=\"#00bfff\" stroke-width=\"1\" stroke-linecap=\"butt\" stroke-linejoin=\"miter\" stroke-miterlimit=\"10\" stroke-dasharray=\"\" stroke-dashoffset=\"0\" font-family=\"none\" font-weight=\"none\" font-size=\"none\" text-anchor=\"none\" style=\"mix-blend-mode: normal\"/></svg>"
                        }
                    },
                    "within": {
                        "@id": "https://iiif.dl.itc.u-tokyo.ac.jp/omekac/oa/items/4403/manifest.json",
                        "@type": "sc:Manifest"
                    }
                }
            ],
            "resource": [
                {
                    "@type": "dctypes:Text",
                    "chars": "<p>A006267-01-0005.jpg_6</p>",
                    "format": "text/html"
                }
            ]
        },
        {
            "@context": "http://iiif.io/api/presentation/2/context.json",
            "@id": "https://iiif.dl.itc.u-tokyo.ac.jp/omekac/oa/items/4554/anno.json",
            "@type": "oa:Annotation",
            "motivation": "oa:commenting",
            "on": [
                {
                    "@type": "oa:SpecificResource",
                    "full": "https://iiif.dl.itc.u-tokyo.ac.jp/repo/iiif/bbe39586-8623-447b-8814-0e19c3986d05/canvas/p5",
                    "selector": {
                        "@type": "oa:Choice",
                        "default": {
                            "@type": "oa:FragmentSelector",
                            "value": "xywh=2559,0,209,5035"
                        },
                        "item": {
                            "@type": "oa:SvgSelector",
                            "value": "<svg xmlns=\"http://www.w3.org/2000/svg\"><path xmlns=\"http://www.w3.org/2000/svg\" d=\"M2768,5035h-209v-5035h209v2517.5z\" data-paper-data=\"{&quot;strokeWidth&quot;:1,&quot;rotation&quot;:0,&quot;deleteIcon&quot;:null,&quot;rotationIcon&quot;:null,&quot;group&quot;:null,&quot;editable&quot;:true,&quot;annotation&quot;:null}\" id=\"rectangle_1d3ebadc-1bcd-4e07-8cc2-c95d2f1865b7\" fill-opacity=\"0\" fill=\"#00bfff\" fill-rule=\"nonzero\" stroke=\"#00bfff\" stroke-width=\"1\" stroke-linecap=\"butt\" stroke-linejoin=\"miter\" stroke-miterlimit=\"10\" stroke-dasharray=\"\" stroke-dashoffset=\"0\" font-family=\"none\" font-weight=\"none\" font-size=\"none\" text-anchor=\"none\" style=\"mix-blend-mode: normal\"/></svg>"
                        }
                    },
                    "within": {
                        "@id": "https://iiif.dl.itc.u-tokyo.ac.jp/omekac/oa/items/4403/manifest.json",
                        "@type": "sc:Manifest"
                    }
                }
            ],
            "resource": [
                {
                    "@type": "dctypes:Text",
                    "chars": "<p>A006267-01-0005.jpg_7</p>",
                    "format": "text/html"
                }
            ]
        },
        {
            "@context": "http://iiif.io/api/presentation/2/context.json",
            "@id": "https://iiif.dl.itc.u-tokyo.ac.jp/omekac/oa/items/4555/anno.json",
            "@type": "oa:Annotation",
            "motivation": "oa:commenting",
            "on": [
                {
                    "@type": "oa:SpecificResource",
                    "full": "https://iiif.dl.itc.u-tokyo.ac.jp/repo/iiif/bbe39586-8623-447b-8814-0e19c3986d05/canvas/p5",
                    "selector": {
                        "@type": "oa:Choice",
                        "default": {
                            "@type": "oa:FragmentSelector",
                            "value": "xywh=2131,0,268,5035"
                        },
                        "item": {
                            "@type": "oa:SvgSelector",
                            "value": "<svg xmlns=\"http://www.w3.org/2000/svg\"><path xmlns=\"http://www.w3.org/2000/svg\" d=\"M2399,5035h-268v-5035h268v2517.5z\" data-paper-data=\"{&quot;strokeWidth&quot;:1,&quot;rotation&quot;:0,&quot;deleteIcon&quot;:null,&quot;rotationIcon&quot;:null,&quot;group&quot;:null,&quot;editable&quot;:true,&quot;annotation&quot;:null}\" id=\"rectangle_1d3ebadc-1bcd-4e07-8cc2-c95d2f1865b7\" fill-opacity=\"0\" fill=\"#00bfff\" fill-rule=\"nonzero\" stroke=\"#00bfff\" stroke-width=\"1\" stroke-linecap=\"butt\" stroke-linejoin=\"miter\" stroke-miterlimit=\"10\" stroke-dasharray=\"\" stroke-dashoffset=\"0\" font-family=\"none\" font-weight=\"none\" font-size=\"none\" text-anchor=\"none\" style=\"mix-blend-mode: normal\"/></svg>"
                        }
                    },
                    "within": {
                        "@id": "https://iiif.dl.itc.u-tokyo.ac.jp/omekac/oa/items/4403/manifest.json",
                        "@type": "sc:Manifest"
                    }
                }
            ],
            "resource": [
                {
                    "@type": "dctypes:Text",
                    "chars": "<p>A006267-01-0005.jpg_8</p>",
                    "format": "text/html"
                }
            ]
        },
        {
            "@context": "http://iiif.io/api/presentation/2/context.json",
            "@id": "https://iiif.dl.itc.u-tokyo.ac.jp/omekac/oa/items/4556/anno.json",
            "@type": "oa:Annotation",
            "motivation": "oa:commenting",
            "on": [
                {
                    "@type": "oa:SpecificResource",
                    "full": "https://iiif.dl.itc.u-tokyo.ac.jp/repo/iiif/bbe39586-8623-447b-8814-0e19c3986d05/canvas/p5",
                    "selector": {
                        "@type": "oa:Choice",
                        "default": {
                            "@type": "oa:FragmentSelector",
                            "value": "xywh=1720,0,268,5035"
                        },
                        "item": {
                            "@type": "oa:SvgSelector",
                            "value": "<svg xmlns=\"http://www.w3.org/2000/svg\"><path xmlns=\"http://www.w3.org/2000/svg\" d=\"M1988,5035h-268v-5035h268v2517.5z\" data-paper-data=\"{&quot;strokeWidth&quot;:1,&quot;rotation&quot;:0,&quot;deleteIcon&quot;:null,&quot;rotationIcon&quot;:null,&quot;group&quot;:null,&quot;editable&quot;:true,&quot;annotation&quot;:null}\" id=\"rectangle_1d3ebadc-1bcd-4e07-8cc2-c95d2f1865b7\" fill-opacity=\"0\" fill=\"#00bfff\" fill-rule=\"nonzero\" stroke=\"#00bfff\" stroke-width=\"1\" stroke-linecap=\"butt\" stroke-linejoin=\"miter\" stroke-miterlimit=\"10\" stroke-dasharray=\"\" stroke-dashoffset=\"0\" font-family=\"none\" font-weight=\"none\" font-size=\"none\" text-anchor=\"none\" style=\"mix-blend-mode: normal\"/></svg>"
                        }
                    },
                    "within": {
                        "@id": "https://iiif.dl.itc.u-tokyo.ac.jp/omekac/oa/items/4403/manifest.json",
                        "@type": "sc:Manifest"
                    }
                }
            ],
            "resource": [
                {
                    "@type": "dctypes:Text",
                    "chars": "<p>A006267-01-0005.jpg_9</p>",
                    "format": "text/html"
                }
            ]
        },
        {
            "@context": "http://iiif.io/api/presentation/2/context.json",
            "@id": "https://iiif.dl.itc.u-tokyo.ac.jp/omekac/oa/items/4557/anno.json",
            "@type": "oa:Annotation",
            "motivation": "oa:commenting",
            "on": [
                {
                    "@type": "oa:SpecificResource",
                    "full": "https://iiif.dl.itc.u-tokyo.ac.jp/repo/iiif/bbe39586-8623-447b-8814-0e19c3986d05/canvas/p5",
                    "selector": {
                        "@type": "oa:Choice",
                        "default": {
                            "@type": "oa:FragmentSelector",
                            "value": "xywh=1309,0,276,5035"
                        },
                        "item": {
                            "@type": "oa:SvgSelector",
                            "value": "<svg xmlns=\"http://www.w3.org/2000/svg\"><path xmlns=\"http://www.w3.org/2000/svg\" d=\"M1585,5035h-276v-5035h276v2517.5z\" data-paper-data=\"{&quot;strokeWidth&quot;:1,&quot;rotation&quot;:0,&quot;deleteIcon&quot;:null,&quot;rotationIcon&quot;:null,&quot;group&quot;:null,&quot;editable&quot;:true,&quot;annotation&quot;:null}\" id=\"rectangle_1d3ebadc-1bcd-4e07-8cc2-c95d2f1865b7\" fill-opacity=\"0\" fill=\"#00bfff\" fill-rule=\"nonzero\" stroke=\"#00bfff\" stroke-width=\"1\" stroke-linecap=\"butt\" stroke-linejoin=\"miter\" stroke-miterlimit=\"10\" stroke-dasharray=\"\" stroke-dashoffset=\"0\" font-family=\"none\" font-weight=\"none\" font-size=\"none\" text-anchor=\"none\" style=\"mix-blend-mode: normal\"/></svg>"
                        }
                    },
                    "within": {
                        "@id": "https://iiif.dl.itc.u-tokyo.ac.jp/omekac/oa/items/4403/manifest.json",
                        "@type": "sc:Manifest"
                    }
                }
            ],
            "resource": [
                {
                    "@type": "dctypes:Text",
                    "chars": "<p>A006267-01-0005.jpg_10</p>",
                    "format": "text/html"
                }
            ]
        }
    ]
}