{
    "@context": "http://www.shared-canvas.org/ns/context.json",
    "@id": "https://raw.githubusercontent.com/nakamura196/omekac_utda/master/docs/oa/items/1601/annolist.json",
    "@type": "sc:AnnotationList",
    "resources": [
        {
            "@context": "http://iiif.io/api/presentation/2/context.json",
            "@id": "https://iiif.dl.itc.u-tokyo.ac.jp/omekac/oa/items/2006/anno.json",
            "@type": "oa:Annotation",
            "motivation": "oa:commenting",
            "on": [
                {
                    "@type": "oa:SpecificResource",
                    "full": "https://iiif.dl.itc.u-tokyo.ac.jp/repo/iiif/d507a810-cff7-4168-bc10-70a32a55920f/canvas/p9",
                    "selector": {
                        "@type": "oa:Choice",
                        "default": {
                            "@type": "oa:FragmentSelector",
                            "value": "xywh=4825,0,207,3840"
                        },
                        "item": {
                            "@type": "oa:SvgSelector",
                            "value": "<svg xmlns=\"http://www.w3.org/2000/svg\"><path xmlns=\"http://www.w3.org/2000/svg\" d=\"M5032,3840h-207v-3840h207v1920.0z\" data-paper-data=\"{&quot;strokeWidth&quot;:1,&quot;rotation&quot;:0,&quot;deleteIcon&quot;:null,&quot;rotationIcon&quot;:null,&quot;group&quot;:null,&quot;editable&quot;:true,&quot;annotation&quot;:null}\" id=\"rectangle_06e92947-fe80-4b4a-b0ca-228018c7beca\" fill-opacity=\"0\" fill=\"#00bfff\" fill-rule=\"nonzero\" stroke=\"#00bfff\" stroke-width=\"1\" stroke-linecap=\"butt\" stroke-linejoin=\"miter\" stroke-miterlimit=\"10\" stroke-dasharray=\"\" stroke-dashoffset=\"0\" font-family=\"none\" font-weight=\"none\" font-size=\"none\" text-anchor=\"none\" style=\"mix-blend-mode: normal\"/></svg>"
                        }
                    },
                    "within": {
                        "@id": "https://raw.githubusercontent.com/nakamura196/omekac_utda/master/docs/oa/items/1601/manifest.json",
                        "@type": "sc:Manifest"
                    }
                }
            ],
            "resource": [
                {
                    "@type": "dctypes:Text",
                    "chars": "<p>一足助次郎淳重申参河國足助庄内仁木郷</p>",
                    "format": "text/plain"
                }
            ]
        },
        {
            "@context": "http://iiif.io/api/presentation/2/context.json",
            "@id": "https://iiif.dl.itc.u-tokyo.ac.jp/omekac/oa/items/2007/anno.json",
            "@type": "oa:Annotation",
            "motivation": "oa:commenting",
            "on": [
                {
                    "@type": "oa:SpecificResource",
                    "full": "https://iiif.dl.itc.u-tokyo.ac.jp/repo/iiif/d507a810-cff7-4168-bc10-70a32a55920f/canvas/p9",
                    "selector": {
                        "@type": "oa:Choice",
                        "default": {
                            "@type": "oa:FragmentSelector",
                            "value": "xywh=4551,0,203,3840"
                        },
                        "item": {
                            "@type": "oa:SvgSelector",
                            "value": "<svg xmlns=\"http://www.w3.org/2000/svg\"><path xmlns=\"http://www.w3.org/2000/svg\" d=\"M4754,3840h-203v-3840h203v1920.0z\" data-paper-data=\"{&quot;strokeWidth&quot;:1,&quot;rotation&quot;:0,&quot;deleteIcon&quot;:null,&quot;rotationIcon&quot;:null,&quot;group&quot;:null,&quot;editable&quot;:true,&quot;annotation&quot;:null}\" id=\"rectangle_06e92947-fe80-4b4a-b0ca-228018c7beca\" fill-opacity=\"0\" fill=\"#00bfff\" fill-rule=\"nonzero\" stroke=\"#00bfff\" stroke-width=\"1\" stroke-linecap=\"butt\" stroke-linejoin=\"miter\" stroke-miterlimit=\"10\" stroke-dasharray=\"\" stroke-dashoffset=\"0\" font-family=\"none\" font-weight=\"none\" font-size=\"none\" text-anchor=\"none\" style=\"mix-blend-mode: normal\"/></svg>"
                        }
                    },
                    "within": {
                        "@id": "https://iiif.dl.itc.u-tokyo.ac.jp/omekac/oa/items/1601/manifest.json",
                        "@type": "sc:Manifest"
                    }
                }
            ],
            "resource": [
                {
                    "@type": "dctypes:Text",
                    "chars": "<p>事先年足助左馬助御敵之時祖父重胤</p>",
                    "format": "text/plain"
                }
            ]
        },
        {
            "@context": "http://iiif.io/api/presentation/2/context.json",
            "@id": "https://iiif.dl.itc.u-tokyo.ac.jp/omekac/oa/items/2010/anno.json",
            "@type": "oa:Annotation",
            "motivation": "oa:commenting",
            "on": [
                {
                    "@type": "oa:SpecificResource",
                    "full": "https://iiif.dl.itc.u-tokyo.ac.jp/repo/iiif/d507a810-cff7-4168-bc10-70a32a55920f/canvas/p9",
                    "selector": {
                        "@type": "oa:Choice",
                        "default": {
                            "@type": "oa:FragmentSelector",
                            "value": "xywh=3685,0,230,3840"
                        },
                        "item": {
                            "@type": "oa:SvgSelector",
                            "value": "<svg xmlns=\"http://www.w3.org/2000/svg\"><path xmlns=\"http://www.w3.org/2000/svg\" d=\"M3915,3840h-230v-3840h230v1920.0z\" data-paper-data=\"{&quot;strokeWidth&quot;:1,&quot;rotation&quot;:0,&quot;deleteIcon&quot;:null,&quot;rotationIcon&quot;:null,&quot;group&quot;:null,&quot;editable&quot;:true,&quot;annotation&quot;:null}\" id=\"rectangle_06e92947-fe80-4b4a-b0ca-228018c7beca\" fill-opacity=\"0\" fill=\"#00bfff\" fill-rule=\"nonzero\" stroke=\"#00bfff\" stroke-width=\"1\" stroke-linecap=\"butt\" stroke-linejoin=\"miter\" stroke-miterlimit=\"10\" stroke-dasharray=\"\" stroke-dashoffset=\"0\" font-family=\"none\" font-weight=\"none\" font-size=\"none\" text-anchor=\"none\" style=\"mix-blend-mode: normal\"/></svg>"
                        }
                    },
                    "within": {
                        "@id": "https://iiif.dl.itc.u-tokyo.ac.jp/omekac/oa/items/1601/manifest.json",
                        "@type": "sc:Manifest"
                    }
                }
            ],
            "resource": [
                {
                    "@type": "dctypes:Text",
                    "chars": "<p>等訖雖然土岐宮内少輔押領之其後土岐御器</p>",
                    "format": "text/plain"
                }
            ]
        },
        {
            "@context": "http://iiif.io/api/presentation/2/context.json",
            "@id": "https://iiif.dl.itc.u-tokyo.ac.jp/omekac/oa/items/2011/anno.json",
            "@type": "oa:Annotation",
            "motivation": "oa:commenting",
            "on": [
                {
                    "@type": "oa:SpecificResource",
                    "full": "https://iiif.dl.itc.u-tokyo.ac.jp/repo/iiif/d507a810-cff7-4168-bc10-70a32a55920f/canvas/p9",
                    "selector": {
                        "@type": "oa:Choice",
                        "default": {
                            "@type": "oa:FragmentSelector",
                            "value": "xywh=3392,0,208,3840"
                        },
                        "item": {
                            "@type": "oa:SvgSelector",
                            "value": "<svg xmlns=\"http://www.w3.org/2000/svg\"><path xmlns=\"http://www.w3.org/2000/svg\" d=\"M3600,3840h-208v-3840h208v1920.0z\" data-paper-data=\"{&quot;strokeWidth&quot;:1,&quot;rotation&quot;:0,&quot;deleteIcon&quot;:null,&quot;rotationIcon&quot;:null,&quot;group&quot;:null,&quot;editable&quot;:true,&quot;annotation&quot;:null}\" id=\"rectangle_06e92947-fe80-4b4a-b0ca-228018c7beca\" fill-opacity=\"0\" fill=\"#00bfff\" fill-rule=\"nonzero\" stroke=\"#00bfff\" stroke-width=\"1\" stroke-linecap=\"butt\" stroke-linejoin=\"miter\" stroke-miterlimit=\"10\" stroke-dasharray=\"\" stroke-dashoffset=\"0\" font-family=\"none\" font-weight=\"none\" font-size=\"none\" text-anchor=\"none\" style=\"mix-blend-mode: normal\"/></svg>"
                        }
                    },
                    "within": {
                        "@id": "https://iiif.dl.itc.u-tokyo.ac.jp/omekac/oa/items/1601/manifest.json",
                        "@type": "sc:Manifest"
                    }
                }
            ],
            "resource": [
                {
                    "@type": "dctypes:Text",
                    "chars": "<p>所知行之刻土岐肥田瀬申給之条難堪也<span style='font-size: 75%'>云々</span></p>",
                    "format": "text/plain"
                }
            ]
        },
        {
            "@context": "http://iiif.io/api/presentation/2/context.json",
            "@id": "https://iiif.dl.itc.u-tokyo.ac.jp/omekac/oa/items/2012/anno.json",
            "@type": "oa:Annotation",
            "motivation": "oa:commenting",
            "on": [
                {
                    "@type": "oa:SpecificResource",
                    "full": "https://iiif.dl.itc.u-tokyo.ac.jp/repo/iiif/d507a810-cff7-4168-bc10-70a32a55920f/canvas/p9",
                    "selector": {
                        "@type": "oa:Choice",
                        "default": {
                            "@type": "oa:FragmentSelector",
                            "value": "xywh=3120,0,207,3840"
                        },
                        "item": {
                            "@type": "oa:SvgSelector",
                            "value": "<svg xmlns=\"http://www.w3.org/2000/svg\"><path xmlns=\"http://www.w3.org/2000/svg\" d=\"M3327,3840h-207v-3840h207v1920.0z\" data-paper-data=\"{&quot;strokeWidth&quot;:1,&quot;rotation&quot;:0,&quot;deleteIcon&quot;:null,&quot;rotationIcon&quot;:null,&quot;group&quot;:null,&quot;editable&quot;:true,&quot;annotation&quot;:null}\" id=\"rectangle_06e92947-fe80-4b4a-b0ca-228018c7beca\" fill-opacity=\"0\" fill=\"#00bfff\" fill-rule=\"nonzero\" stroke=\"#00bfff\" stroke-width=\"1\" stroke-linecap=\"butt\" stroke-linejoin=\"miter\" stroke-miterlimit=\"10\" stroke-dasharray=\"\" stroke-dashoffset=\"0\" font-family=\"none\" font-weight=\"none\" font-size=\"none\" text-anchor=\"none\" style=\"mix-blend-mode: normal\"/></svg>"
                        }
                    },
                    "within": {
                        "@id": "https://iiif.dl.itc.u-tokyo.ac.jp/omekac/oa/items/1601/manifest.json",
                        "@type": "sc:Manifest"
                    }
                }
            ],
            "resource": [
                {
                    "@type": "dctypes:Text",
                    "chars": "<p>肥田瀬宮内大輔支状云為御器所拜領之間稱</p>",
                    "format": "text/plain"
                }
            ]
        },
        {
            "@context": "http://iiif.io/api/presentation/2/context.json",
            "@id": "https://iiif.dl.itc.u-tokyo.ac.jp/omekac/oa/items/2013/anno.json",
            "@type": "oa:Annotation",
            "motivation": "oa:commenting",
            "on": [
                {
                    "@type": "oa:SpecificResource",
                    "full": "https://iiif.dl.itc.u-tokyo.ac.jp/repo/iiif/d507a810-cff7-4168-bc10-70a32a55920f/canvas/p9",
                    "selector": {
                        "@type": "oa:Choice",
                        "default": {
                            "@type": "oa:FragmentSelector",
                            "value": "xywh=2845,0,194,3840"
                        },
                        "item": {
                            "@type": "oa:SvgSelector",
                            "value": "<svg xmlns=\"http://www.w3.org/2000/svg\"><path xmlns=\"http://www.w3.org/2000/svg\" d=\"M3039,3840h-194v-3840h194v1920.0z\" data-paper-data=\"{&quot;strokeWidth&quot;:1,&quot;rotation&quot;:0,&quot;deleteIcon&quot;:null,&quot;rotationIcon&quot;:null,&quot;group&quot;:null,&quot;editable&quot;:true,&quot;annotation&quot;:null}\" id=\"rectangle_06e92947-fe80-4b4a-b0ca-228018c7beca\" fill-opacity=\"0\" fill=\"#00bfff\" fill-rule=\"nonzero\" stroke=\"#00bfff\" stroke-width=\"1\" stroke-linecap=\"butt\" stroke-linejoin=\"miter\" stroke-miterlimit=\"10\" stroke-dasharray=\"\" stroke-dashoffset=\"0\" font-family=\"none\" font-weight=\"none\" font-size=\"none\" text-anchor=\"none\" style=\"mix-blend-mode: normal\"/></svg>"
                        }
                    },
                    "within": {
                        "@id": "https://iiif.dl.itc.u-tokyo.ac.jp/omekac/oa/items/1601/manifest.json",
                        "@type": "sc:Manifest"
                    }
                }
            ],
            "resource": [
                {
                    "@type": "dctypes:Text",
                    "chars": "<p>本主歎申之条更無其謂<span style='font-size: 75%'>云々</span>所詮足助有勲</p>",
                    "format": "text/plain"
                }
            ]
        },
        {
            "@context": "http://iiif.io/api/presentation/2/context.json",
            "@id": "https://iiif.dl.itc.u-tokyo.ac.jp/omekac/oa/items/2014/anno.json",
            "@type": "oa:Annotation",
            "motivation": "oa:commenting",
            "on": [
                {
                    "@type": "oa:SpecificResource",
                    "full": "https://iiif.dl.itc.u-tokyo.ac.jp/repo/iiif/d507a810-cff7-4168-bc10-70a32a55920f/canvas/p9",
                    "selector": {
                        "@type": "oa:Choice",
                        "default": {
                            "@type": "oa:FragmentSelector",
                            "value": "xywh=2230,0,214,3840"
                        },
                        "item": {
                            "@type": "oa:SvgSelector",
                            "value": "<svg xmlns=\"http://www.w3.org/2000/svg\"><path xmlns=\"http://www.w3.org/2000/svg\" d=\"M2444,3840h-214v-3840h214v1920.0z\" data-paper-data=\"{&quot;strokeWidth&quot;:1,&quot;rotation&quot;:0,&quot;deleteIcon&quot;:null,&quot;rotationIcon&quot;:null,&quot;group&quot;:null,&quot;editable&quot;:true,&quot;annotation&quot;:null}\" id=\"rectangle_06e92947-fe80-4b4a-b0ca-228018c7beca\" fill-opacity=\"0\" fill=\"#00bfff\" fill-rule=\"nonzero\" stroke=\"#00bfff\" stroke-width=\"1\" stroke-linecap=\"butt\" stroke-linejoin=\"miter\" stroke-miterlimit=\"10\" stroke-dasharray=\"\" stroke-dashoffset=\"0\" font-family=\"none\" font-weight=\"none\" font-size=\"none\" text-anchor=\"none\" style=\"mix-blend-mode: normal\"/></svg>"
                        }
                    },
                    "within": {
                        "@id": "https://iiif.dl.itc.u-tokyo.ac.jp/omekac/oa/items/1601/manifest.json",
                        "@type": "sc:Manifest"
                    }
                }
            ],
            "resource": [
                {
                    "@type": "dctypes:Text",
                    "chars": "<p>功無其誤之上者任證文等之旨被下還補</p>",
                    "format": "text/plain"
                }
            ]
        },
        {
            "@context": "http://iiif.io/api/presentation/2/context.json",
            "@id": "https://iiif.dl.itc.u-tokyo.ac.jp/omekac/oa/items/2015/anno.json",
            "@type": "oa:Annotation",
            "motivation": "oa:commenting",
            "on": [
                {
                    "@type": "oa:SpecificResource",
                    "full": "https://iiif.dl.itc.u-tokyo.ac.jp/repo/iiif/d507a810-cff7-4168-bc10-70a32a55920f/canvas/p9",
                    "selector": {
                        "@type": "oa:Choice",
                        "default": {
                            "@type": "oa:FragmentSelector",
                            "value": "xywh=1944,0,155,3840"
                        },
                        "item": {
                            "@type": "oa:SvgSelector",
                            "value": "<svg xmlns=\"http://www.w3.org/2000/svg\"><path xmlns=\"http://www.w3.org/2000/svg\" d=\"M2099,3840h-155v-3840h155v1920.0z\" data-paper-data=\"{&quot;strokeWidth&quot;:1,&quot;rotation&quot;:0,&quot;deleteIcon&quot;:null,&quot;rotationIcon&quot;:null,&quot;group&quot;:null,&quot;editable&quot;:true,&quot;annotation&quot;:null}\" id=\"rectangle_06e92947-fe80-4b4a-b0ca-228018c7beca\" fill-opacity=\"0\" fill=\"#00bfff\" fill-rule=\"nonzero\" stroke=\"#00bfff\" stroke-width=\"1\" stroke-linecap=\"butt\" stroke-linejoin=\"miter\" stroke-miterlimit=\"10\" stroke-dasharray=\"\" stroke-dashoffset=\"0\" font-family=\"none\" font-weight=\"none\" font-size=\"none\" text-anchor=\"none\" style=\"mix-blend-mode: normal\"/></svg>"
                        }
                    },
                    "within": {
                        "@id": "https://iiif.dl.itc.u-tokyo.ac.jp/omekac/oa/items/1601/manifest.json",
                        "@type": "sc:Manifest"
                    }
                }
            ],
            "resource": [
                {
                    "@type": "dctypes:Text",
                    "chars": "<p>御判於淳重訖</p>",
                    "format": "text/plain"
                }
            ]
        },
        {
            "@context": "http://iiif.io/api/presentation/2/context.json",
            "@id": "https://iiif.dl.itc.u-tokyo.ac.jp/omekac/oa/items/2016/anno.json",
            "@type": "oa:Annotation",
            "motivation": "oa:commenting",
            "on": [
                {
                    "@type": "oa:SpecificResource",
                    "full": "https://iiif.dl.itc.u-tokyo.ac.jp/repo/iiif/d507a810-cff7-4168-bc10-70a32a55920f/canvas/p9",
                    "selector": {
                        "@type": "oa:Choice",
                        "default": {
                            "@type": "oa:FragmentSelector",
                            "value": "xywh=1656,0,195,3840"
                        },
                        "item": {
                            "@type": "oa:SvgSelector",
                            "value": "<svg xmlns=\"http://www.w3.org/2000/svg\"><path xmlns=\"http://www.w3.org/2000/svg\" d=\"M1851,3840h-195v-3840h195v1920.0z\" data-paper-data=\"{&quot;strokeWidth&quot;:1,&quot;rotation&quot;:0,&quot;deleteIcon&quot;:null,&quot;rotationIcon&quot;:null,&quot;group&quot;:null,&quot;editable&quot;:true,&quot;annotation&quot;:null}\" id=\"rectangle_06e92947-fe80-4b4a-b0ca-228018c7beca\" fill-opacity=\"0\" fill=\"#00bfff\" fill-rule=\"nonzero\" stroke=\"#00bfff\" stroke-width=\"1\" stroke-linecap=\"butt\" stroke-linejoin=\"miter\" stroke-miterlimit=\"10\" stroke-dasharray=\"\" stroke-dashoffset=\"0\" font-family=\"none\" font-weight=\"none\" font-size=\"none\" text-anchor=\"none\" style=\"mix-blend-mode: normal\"/></svg>"
                        }
                    },
                    "within": {
                        "@id": "https://iiif.dl.itc.u-tokyo.ac.jp/omekac/oa/items/1601/manifest.json",
                        "@type": "sc:Manifest"
                    }
                }
            ],
            "resource": [
                {
                    "@type": "dctypes:Text",
                    "chars": "<p>土肥次郎貞平窮困事管領被執申之仍</p>",
                    "format": "text/plain"
                }
            ]
        },
        {
            "@context": "http://iiif.io/api/presentation/2/context.json",
            "@id": "https://iiif.dl.itc.u-tokyo.ac.jp/omekac/oa/items/2017/anno.json",
            "@type": "oa:Annotation",
            "motivation": "oa:commenting",
            "on": [
                {
                    "@type": "oa:SpecificResource",
                    "full": "https://iiif.dl.itc.u-tokyo.ac.jp/repo/iiif/d507a810-cff7-4168-bc10-70a32a55920f/canvas/p9",
                    "selector": {
                        "@type": "oa:Choice",
                        "default": {
                            "@type": "oa:FragmentSelector",
                            "value": "xywh=1360,0,185,3840"
                        },
                        "item": {
                            "@type": "oa:SvgSelector",
                            "value": "<svg xmlns=\"http://www.w3.org/2000/svg\"><path xmlns=\"http://www.w3.org/2000/svg\" d=\"M1545,3840h-185v-3840h185v1920.0z\" data-paper-data=\"{&quot;strokeWidth&quot;:1,&quot;rotation&quot;:0,&quot;deleteIcon&quot;:null,&quot;rotationIcon&quot;:null,&quot;group&quot;:null,&quot;editable&quot;:true,&quot;annotation&quot;:null}\" id=\"rectangle_06e92947-fe80-4b4a-b0ca-228018c7beca\" fill-opacity=\"0\" fill=\"#00bfff\" fill-rule=\"nonzero\" stroke=\"#00bfff\" stroke-width=\"1\" stroke-linecap=\"butt\" stroke-linejoin=\"miter\" stroke-miterlimit=\"10\" stroke-dasharray=\"\" stroke-dashoffset=\"0\" font-family=\"none\" font-weight=\"none\" font-size=\"none\" text-anchor=\"none\" style=\"mix-blend-mode: normal\"/></svg>"
                        }
                    },
                    "within": {
                        "@id": "https://iiif.dl.itc.u-tokyo.ac.jp/omekac/oa/items/1601/manifest.json",
                        "@type": "sc:Manifest"
                    }
                }
            ],
            "resource": [
                {
                    "@type": "dctypes:Text",
                    "chars": "<p>不可有准據之儀限一人以契約在所可申</p>",
                    "format": "text/plain"
                }
            ]
        },
        {
            "@context": "http://iiif.io/api/presentation/2/context.json",
            "@id": "https://iiif.dl.itc.u-tokyo.ac.jp/omekac/oa/items/2018/anno.json",
            "@type": "oa:Annotation",
            "motivation": "oa:commenting",
            "on": [
                {
                    "@type": "oa:SpecificResource",
                    "full": "https://iiif.dl.itc.u-tokyo.ac.jp/repo/iiif/d507a810-cff7-4168-bc10-70a32a55920f/canvas/p9",
                    "selector": {
                        "@type": "oa:Choice",
                        "default": {
                            "@type": "oa:FragmentSelector",
                            "value": "xywh=1071,0,195,3840"
                        },
                        "item": {
                            "@type": "oa:SvgSelector",
                            "value": "<svg xmlns=\"http://www.w3.org/2000/svg\"><path xmlns=\"http://www.w3.org/2000/svg\" d=\"M1266,3840h-195v-3840h195v1920.0z\" data-paper-data=\"{&quot;strokeWidth&quot;:1,&quot;rotation&quot;:0,&quot;deleteIcon&quot;:null,&quot;rotationIcon&quot;:null,&quot;group&quot;:null,&quot;editable&quot;:true,&quot;annotation&quot;:null}\" id=\"rectangle_06e92947-fe80-4b4a-b0ca-228018c7beca\" fill-opacity=\"0\" fill=\"#00bfff\" fill-rule=\"nonzero\" stroke=\"#00bfff\" stroke-width=\"1\" stroke-linecap=\"butt\" stroke-linejoin=\"miter\" stroke-miterlimit=\"10\" stroke-dasharray=\"\" stroke-dashoffset=\"0\" font-family=\"none\" font-weight=\"none\" font-size=\"none\" text-anchor=\"none\" style=\"mix-blend-mode: normal\"/></svg>"
                        }
                    },
                    "within": {
                        "@id": "https://iiif.dl.itc.u-tokyo.ac.jp/omekac/oa/items/1601/manifest.json",
                        "@type": "sc:Manifest"
                    }
                }
            ],
            "resource": [
                {
                    "@type": "dctypes:Text",
                    "chars": "<p>旨被仰出之間以此在所申請令契約訖</p>",
                    "format": "text/plain"
                }
            ]
        },
        {
            "@context": "http://iiif.io/api/presentation/2/context.json",
            "@id": "https://iiif.dl.itc.u-tokyo.ac.jp/omekac/oa/items/2019/anno.json",
            "@type": "oa:Annotation",
            "motivation": "oa:commenting",
            "on": [
                {
                    "@type": "oa:SpecificResource",
                    "full": "https://iiif.dl.itc.u-tokyo.ac.jp/repo/iiif/d507a810-cff7-4168-bc10-70a32a55920f/canvas/p9",
                    "selector": {
                        "@type": "oa:Choice",
                        "default": {
                            "@type": "oa:FragmentSelector",
                            "value": "xywh=786,0,194,3840"
                        },
                        "item": {
                            "@type": "oa:SvgSelector",
                            "value": "<svg xmlns=\"http://www.w3.org/2000/svg\"><path xmlns=\"http://www.w3.org/2000/svg\" d=\"M980,3840h-194v-3840h194v1920.0z\" data-paper-data=\"{&quot;strokeWidth&quot;:1,&quot;rotation&quot;:0,&quot;deleteIcon&quot;:null,&quot;rotationIcon&quot;:null,&quot;group&quot;:null,&quot;editable&quot;:true,&quot;annotation&quot;:null}\" id=\"rectangle_06e92947-fe80-4b4a-b0ca-228018c7beca\" fill-opacity=\"0\" fill=\"#00bfff\" fill-rule=\"nonzero\" stroke=\"#00bfff\" stroke-width=\"1\" stroke-linecap=\"butt\" stroke-linejoin=\"miter\" stroke-miterlimit=\"10\" stroke-dasharray=\"\" stroke-dashoffset=\"0\" font-family=\"none\" font-weight=\"none\" font-size=\"none\" text-anchor=\"none\" style=\"mix-blend-mode: normal\"/></svg>"
                        }
                    },
                    "within": {
                        "@id": "https://iiif.dl.itc.u-tokyo.ac.jp/omekac/oa/items/1601/manifest.json",
                        "@type": "sc:Manifest"
                    }
                }
            ],
            "resource": [
                {
                    "@type": "dctypes:Text",
                    "chars": "<p>即不謂御銘之次第令披露者也<span style='font-size: 75%'>焉</span></p>",
                    "format": "text/plain"
                }
            ]
        },
        {
            "@context": "http://iiif.io/api/presentation/2/context.json",
            "@id": "https://iiif.dl.itc.u-tokyo.ac.jp/omekac/oa/items/2020/anno.json",
            "@type": "oa:Annotation",
            "motivation": "oa:commenting",
            "on": [
                {
                    "@type": "oa:SpecificResource",
                    "full": "https://iiif.dl.itc.u-tokyo.ac.jp/repo/iiif/d507a810-cff7-4168-bc10-70a32a55920f/canvas/p9",
                    "selector": {
                        "@type": "oa:Choice",
                        "default": {
                            "@type": "oa:FragmentSelector",
                            "value": "xywh=516,0,226,3840"
                        },
                        "item": {
                            "@type": "oa:SvgSelector",
                            "value": "<svg xmlns=\"http://www.w3.org/2000/svg\"><path xmlns=\"http://www.w3.org/2000/svg\" d=\"M742,3840h-226v-3840h226v1920.0z\" data-paper-data=\"{&quot;strokeWidth&quot;:1,&quot;rotation&quot;:0,&quot;deleteIcon&quot;:null,&quot;rotationIcon&quot;:null,&quot;group&quot;:null,&quot;editable&quot;:true,&quot;annotation&quot;:null}\" id=\"rectangle_06e92947-fe80-4b4a-b0ca-228018c7beca\" fill-opacity=\"0\" fill=\"#00bfff\" fill-rule=\"nonzero\" stroke=\"#00bfff\" stroke-width=\"1\" stroke-linecap=\"butt\" stroke-linejoin=\"miter\" stroke-miterlimit=\"10\" stroke-dasharray=\"\" stroke-dashoffset=\"0\" font-family=\"none\" font-weight=\"none\" font-size=\"none\" text-anchor=\"none\" style=\"mix-blend-mode: normal\"/></svg>"
                        }
                    },
                    "within": {
                        "@id": "https://iiif.dl.itc.u-tokyo.ac.jp/omekac/oa/items/1601/manifest.json",
                        "@type": "sc:Manifest"
                    }
                }
            ],
            "resource": [
                {
                    "@type": "dctypes:Text",
                    "chars": "<p>永享二年九月十八日　肥前守為種（花押）</p>",
                    "format": "text/plain"
                }
            ]
        },
        {
            "@context": "http://iiif.io/api/presentation/2/context.json",
            "@id": "https://iiif.dl.itc.u-tokyo.ac.jp/omekac/oa/items/2021/anno.json",
            "@type": "oa:Annotation",
            "motivation": "oa:commenting",
            "on": [
                {
                    "@type": "oa:SpecificResource",
                    "full": "https://iiif.dl.itc.u-tokyo.ac.jp/repo/iiif/d507a810-cff7-4168-bc10-70a32a55920f/canvas/p9",
                    "selector": {
                        "@type": "oa:Choice",
                        "default": {
                            "@type": "oa:FragmentSelector",
                            "value": "xywh=240,0,168,3840"
                        },
                        "item": {
                            "@type": "oa:SvgSelector",
                            "value": "<svg xmlns=\"http://www.w3.org/2000/svg\"><path xmlns=\"http://www.w3.org/2000/svg\" d=\"M408,3840h-168v-3840h168v1920.0z\" data-paper-data=\"{&quot;strokeWidth&quot;:1,&quot;rotation&quot;:0,&quot;deleteIcon&quot;:null,&quot;rotationIcon&quot;:null,&quot;group&quot;:null,&quot;editable&quot;:true,&quot;annotation&quot;:null}\" id=\"rectangle_06e92947-fe80-4b4a-b0ca-228018c7beca\" fill-opacity=\"0\" fill=\"#00bfff\" fill-rule=\"nonzero\" stroke=\"#00bfff\" stroke-width=\"1\" stroke-linecap=\"butt\" stroke-linejoin=\"miter\" stroke-miterlimit=\"10\" stroke-dasharray=\"\" stroke-dashoffset=\"0\" font-family=\"none\" font-weight=\"none\" font-size=\"none\" text-anchor=\"none\" style=\"mix-blend-mode: normal\"/></svg>"
                        }
                    },
                    "within": {
                        "@id": "https://iiif.dl.itc.u-tokyo.ac.jp/omekac/oa/items/1601/manifest.json",
                        "@type": "sc:Manifest"
                    }
                }
            ],
            "resource": [
                {
                    "@type": "dctypes:Text",
                    "chars": "<p>加賀守基貞（花押）</p>",
                    "format": "text/plain"
                }
            ]
        },
        {
            "@context": "http://iiif.io/api/presentation/2/context.json",
            "@id": "https://iiif.dl.itc.u-tokyo.ac.jp/omekac/oa/items/3690/anno.json",
            "@type": "oa:Annotation",
            "motivation": "oa:commenting",
            "on": [
                {
                    "@type": "oa:SpecificResource",
                    "full": "https://iiif.dl.itc.u-tokyo.ac.jp/repo/iiif/d507a810-cff7-4168-bc10-70a32a55920f/canvas/p9",
                    "selector": {
                        "@type": "oa:Choice",
                        "default": {
                            "@type": "oa:FragmentSelector",
                            "value": "xywh=3945,0,245,3824"
                        },
                        "item": {
                            "@type": "oa:SvgSelector",
                            "value": "<svg xmlns='http://www.w3.org/2000/svg'><path xmlns=\"http://www.w3.org/2000/svg\" d=\"M3945.47653,3824.13718h122.29964v0h122.29964v-1912.06859v-1912.06859h-122.29964h-122.29964v1912.06859z\" data-paper-data=\"{&quot;strokeWidth&quot;:1,&quot;rotation&quot;:0,&quot;deleteIcon&quot;:null,&quot;rotationIcon&quot;:null,&quot;group&quot;:null,&quot;editable&quot;:true,&quot;annotation&quot;:null}\" id=\"rectangle_bdb8bae6-b43c-4c0b-9ebf-9d58dd5cfe16\" fill-opacity=\"0\" fill=\"#00bfff\" fill-rule=\"nonzero\" stroke=\"#00bfff\" stroke-width=\"1\" stroke-linecap=\"butt\" stroke-linejoin=\"miter\" stroke-miterlimit=\"10\" stroke-dasharray=\"\" stroke-dashoffset=\"0\" font-family=\"none\" font-weight=\"none\" font-size=\"none\" text-anchor=\"none\" style=\"mix-blend-mode: normal\"/></svg>"
                        }
                    },
                    "within": {
                        "@id": "https://iiif.dl.itc.u-tokyo.ac.jp/omekac/oa/items/1601/manifest.json",
                        "@type": "sc:Manifest"
                    }
                }
            ],
            "resource": [
                {
                    "@type": "dctypes:Text",
                    "chars": "<p>被聞食披被召出之致忠節被下還補御判</p>",
                    "format": "text/html"
                }
            ]
        },
        {
            "@context": "http://iiif.io/api/presentation/2/context.json",
            "@id": "https://iiif.dl.itc.u-tokyo.ac.jp/omekac/oa/items/3691/anno.json",
            "@type": "oa:Annotation",
            "motivation": "oa:commenting",
            "on": [
                {
                    "@type": "oa:SpecificResource",
                    "full": "https://iiif.dl.itc.u-tokyo.ac.jp/repo/iiif/d507a810-cff7-4168-bc10-70a32a55920f/canvas/p9",
                    "selector": {
                        "@type": "oa:Choice",
                        "default": {
                            "@type": "oa:FragmentSelector",
                            "value": "xywh=4216,-2,307,3844"
                        },
                        "item": {
                            "@type": "oa:SvgSelector",
                            "value": "<svg xmlns='http://www.w3.org/2000/svg'><path xmlns=\"http://www.w3.org/2000/svg\" d=\"M4215.80144,-2h153.49097v0h153.49097v1922v1922h-153.49097h-153.49097v-1922z\" data-paper-data=\"{&quot;strokeWidth&quot;:1,&quot;rotation&quot;:0,&quot;deleteIcon&quot;:null,&quot;rotationIcon&quot;:null,&quot;group&quot;:null,&quot;editable&quot;:true,&quot;annotation&quot;:null}\" id=\"rectangle_a70de80e-1e8b-4f6d-ae42-9671e40529ab\" fill-opacity=\"0\" fill=\"#00bfff\" fill-rule=\"nonzero\" stroke=\"#00bfff\" stroke-width=\"1\" stroke-linecap=\"butt\" stroke-linejoin=\"miter\" stroke-miterlimit=\"10\" stroke-dasharray=\"\" stroke-dashoffset=\"0\" font-family=\"none\" font-weight=\"none\" font-size=\"none\" text-anchor=\"none\" style=\"mix-blend-mode: normal\"/></svg>"
                        }
                    },
                    "within": {
                        "@id": "https://iiif.dl.itc.u-tokyo.ac.jp/omekac/oa/items/1601/manifest.json",
                        "@type": "sc:Manifest"
                    }
                }
            ],
            "resource": [
                {
                    "@type": "dctypes:Text",
                    "chars": "<p><span style='color:#ff0000'>左馬助舎弟</span>雖令諷諫不承引仕之間隠居仕之處</p>",
                    "format": "text/html"
                }
            ]
        }
    ]
}